[{
        "id": "1",
        "name": "Casa mia!",
        "brand": "Generali",
        "brandImage": "brand_generali.png",
        "kind": "Hogar",
        "kindImage": "kind_home.png",
        "price": "300"
    },
    {
        "id": "2",
        "name": "No eres imortal",
        "brand": "Mapfre",
        "brandImage": "brand_mapfre.png",
        "kind": "Vida",
        "kindImage": "kind_life.png",
        "price": "100"
    },
    {
        "id": "3",
        "name": "Panacea",
        "brand": "Zurich",
        "brandImage": "brand_zurich.png",
        "kind": "Viaje",
        "kindImage": "kind_travel.png",
        "price": "50"
    },
    {
        "id": "4",
        "name": "<mis_datos>",
        "brand": "AXA",
        "brandImage": "brand_axa.png",
        "kind": "cybersecurity",
        "kindImage": "kind_cybersecurity.png",
        "price": "1010"
    },
    {
        "id": "5",
        "name": "Cuidado con el peatón",
        "brand": "Liberty",
        "brandImage": "brand_liberty.png",
        "kind": "Coche",
        "kindImage": "kind_car.png",
        "price": "120"
    },
    {
        "id": "6",
        "name": "Sargento de hierro",
        "brand": "Zurich",
        "brandImage": "brand_zurich.png",
        "kind": "Salud",
        "kindImage": "kind_health.png",
        "price": "97"
    },
    {
        "id": "7",
        "name": "Currante non stop",
        "brand": "Mapfre",
        "brandImage": "brand_mapfre.png",
        "kind": "Trabajo",
        "kindImage": "kind_work.png",
        "price": "2001"
    },
    {
        "id": "8",
        "name": "Brum! Brum!",
        "brand": "Liberty",
        "brandImage": "brand_liberty.png",
        "kind": "Coche",
        "kindImage": "kind_car.png",
        "price": "120"
    },
    {
        "id": "9",
        "name": "Gandalf",
        "brand": "generali",
        "brandImage": "brand_generali.png",
        "kind": "cybersecurity",
        "kindImage": "kind_cybersecurity.png",
        "price": "2010"
    },
    {
        "id": "10",
        "name": "Relajate",
        "brand": "Zurich",
        "brandImage": "brand_zurich.png",
        "kind": "Viaje",
        "kindImage": "kind_travel.png",
        "price": "55"
    },
    {
        "id": "11",
        "name": "Cuidate mucho",
        "brand": "AXA",
        "brandImage": "brand_axa.png",
        "kind": "Salud",
        "kindImage": "kind_health.png",
        "price": "256"
    },
    {
        "id": "12",
        "name": "Fort Nox",
        "brand": "Liberty",
        "brandImage": "brand_liberty.png",
        "kind": "Hogar",
        "kindImage": "kind_home.png",
        "price": "500"
    },
    {
        "id": "13",
        "name": "Micheal Knight & KIT",
        "brand": "Generali",
        "brandImage": "brand_generali.png",
        "kind": "Coche",
        "kindImage": "kind_car.png",
        "price": "1982"
    },
    {
        "id": "14",
        "name": "Como un Golem",
        "brand": "AXA",
        "brandImage": "brand_axa.png",
        "kind": "Salud",
        "kindImage": "kind_health.png",
        "price": "123"
    },
    {
        "id": "15",
        "name": "Hombre Cafeina",
        "brand": "Zurich",
        "brandImage": "brand_zurich.png",
        "kind": "Trabajo",
        "kindImage": "kind_work.png",
        "price": "55"
    },
    {
        "id": "16",
        "name": "No más lemmings",
        "brand": "Mapfre",
        "brandImage": "brand_mapfre.png",
        "kind": "Cybersecurity",
        "kindImage": "kind_cybersecurity.png",
        "price": "500"
    },
    {
        "id": "17",
        "name": "Haz el piropuente",
        "brand": "Generali",
        "brandImage": "brand_generali.png",
        "kind": "Viaje",
        "kindImage": "kind_travel.png",
        "price": "45"
    },
    {
        "id": "18",
        "name": "Para que no te lloren tanto",
        "brand": "Mapfre",
        "brandImage": "brand_mapfre.png",
        "kind": "Vida",
        "kindImage": "kind_life.png",
        "price": "81"
    },
    {
        "id": "19",
        "name": "Mii miiiii",
        "brand": "Zurich",
        "brandImage": "brand_zurich.png",
        "kind": "Coche",
        "kindImage": "kind_car.png",
        "price": "35"
    },
    {
        "id": "20",
        "name": "Nerver Jubilado",
        "brand": "Liberty",
        "brandImage": "brand_liberty.png",
        "kind": "Trabajo",
        "kindImage": "kind_work.png",
        "price": "56"
    },
    {
        "id": "21",
        "name": "Foso de cocodrilos",
        "brand": "AXA",
        "brandImage": "brand_axa.png",
        "kind": "Hogar",
        "kindImage": "kind_home.png",
        "price": "50000"
    },
    {
        "id": "22",
        "name": "Be Barry Allen",
        "brand": "Generali",
        "brandImage": "brand_generali.png",
        "kind": "Coche",
        "kindImage": "kind_car.png",
        "price": "444"
    },
    {
        "id": "23",
        "name": "Mr.Norton",
        "brand": "Liberty",
        "brandImage": "brand_liberty.png",
        "kind": "Cybersecurity",
        "kindImage": "kind_cybersecurity.png",
        "price": "360"
    },
    {
        "id": "24",
        "name": "Castaway",
        "brand": "Zurich",
        "brandImage": "brand_zurich.png",
        "kind": "Viaje",
        "kindImage": "kind_travel.png",
        "price": "9"
    },
    {
        "id": "25",
        "name": "Se te ha caído el boli",
        "brand": "Generali",
        "brandImage": "brand_generali.png",
        "kind": "Trabajo",
        "kindImage": "kind_work.png",
        "price": "300"
    },
    {
        "id": "26",
        "name": "Masajes y relax",
        "brand": "AXA",
        "brandImage": "brand_axa.png",
        "kind": "Viaje",
        "kindImage": "kind_travel.png",
        "price": "512"
    },
    {
        "id": "27",
        "name": "Cerra la maldita puerta",
        "brand": "Mapfre",
        "brandImage": "brand_mapfre.png",
        "kind": "Hogar",
        "kindImage": "kind_home.png",
        "price": "1000"
    },
    {
        "id": "28",
        "name": "ESC\\#??$.[SHIFT][RUN][ENTER]8.32!Out of memory",
        "brand": "Zurich",
        "brandImage": "brand_zurich.png",
        "kind": "Cybersecurity",
        "kindImage": "kind_cybersecurity.png",
        "price": "832"
    },
    {
        "id": "29",
        "name": "Luke, yo soy tu padre",
        "brand": "Liberty",
        "brandImage": "brand_liberty.png",
        "kind": "Vida",
        "kindImage": "kind_life.png",
        "price": "707"
    },
    {
        "id": "30",
        "name": "Feed the troll",
        "brand": "Generali",
        "brandImage": "brand_generali.png",
        "kind": "Salud",
        "kindImage": "kind_health.png",
        "price": "333"
    },
    {
        "id": "31",
        "name": "Work sweet work",
        "brand": "Zurich",
        "brandImage": "brand_zurich.png",
        "kind": "Trabajo",
        "kindImage": "kind_work.png",
        "price": "120"
    },
    {
        "id": "32",
        "name": "Safe & Sound",
        "brand": "Mapfre",
        "brandImage": "brand_mapfre.png",
        "kind": "Coche",
        "kindImage": "kind_car.png",
        "price": "66"
    },
    {
        "id": "33",
        "name": "Por fin se acabo",
        "brand": "AXA",
        "brandImage": "brand_axa.png",
        "kind": "Vida",
        "kindImage": "kind_life.png",
        "price": "1234"
    }
]